query_toolkits/__init__.py
query_toolkits/error_correction.py
query_toolkits/extractor.py
query_toolkits/financial_index.txt
query_toolkits/financial_index_full.txt
query_toolkits/fund_product.txt
query_toolkits/index.txt
query_toolkits/info.json
query_toolkits/keyword.txt
query_toolkits/organization.txt
query_toolkits/product.txt
query_toolkits/unit_transform
query_toolkits/utils.py
query_toolkits/weapon.txt
query_toolkits-1.3.0.dist-info/METADATA
query_toolkits-1.3.0.dist-info/WHEEL
query_toolkits-1.3.0.dist-info/top_level.txt
query_toolkits-1.3.0.dist-info/RECORD
