Metadata-Version: 2.1
Name: query-toolkits
Version: 1.3.0
Summary: version
Home-page: https://pypi.org/project/query_toolkits
Author: huyi
Author-email: cracks@yeah.net
Requires-Python: >=3.6.0
Requires-Dist: regex (==2022.7.25)
